plone.app.i18n-4.0.2-py3.13-nspkg.pth
plone/app/i18n/__init__.py
plone/app/i18n/configure.zcml
plone/app/i18n/tool.gif
plone/app/i18n/locales/__init__.py
plone/app/i18n/locales/configure.zcml
plone/app/i18n/locales/countries.py
plone/app/i18n/locales/interfaces.py
plone/app/i18n/locales/languages.py
plone/app/i18n/locales/browser/__init__.py
plone/app/i18n/locales/browser/configure.zcml
plone/app/i18n/locales/browser/languageselector.pt
plone/app/i18n/locales/browser/selector.py
plone/app/i18n/locales/browser/tests.py
plone/app/i18n/locales/tests/__init__.py
plone/app/i18n/locales/tests/countries.txt
plone/app/i18n/locales/tests/languages.txt
plone/app/i18n/locales/tests/test_doctests.py
plone_app_i18n-4.0.2.dist-info/METADATA
plone_app_i18n-4.0.2.dist-info/WHEEL
plone_app_i18n-4.0.2.dist-info/namespace_packages.txt
plone_app_i18n-4.0.2.dist-info/top_level.txt
plone_app_i18n-4.0.2.dist-info/RECORD
